ebib/__init__.py
ebib/cli.py
ebib/english_stemmer.py
ebib/indexer.py
ebib/lexer.py
ebib/utils.py
ebib/assets/.gitlab-ci.yml
ebib/assets/english-stemmer.js
ebib/assets/index.html
ebib/assets/index.js
ebib-1.2.1.dist-info/LICENSE
ebib-1.2.1.dist-info/METADATA
ebib-1.2.1.dist-info/WHEEL
ebib-1.2.1.dist-info/entry_points.txt
ebib-1.2.1.dist-info/top_level.txt
ebib-1.2.1.dist-info/RECORD
