Metadata-Version: 2.1
Name: ebib
Version: 1.2.1
Summary: ebib is a bibliography manager system aimed to work with Gitlab/Github pages
Author-email: Ernesto Lanchares <elancha98@gmail.com>
Project-URL: Homepage, https://gitlab.com/elancha/ebib
Project-URL: Bug Tracker, https://gitlab.com/elancha/ebib/issues
Requires-Python: >=3.7
License-File: LICENSE
Requires-Dist: Click
Requires-Dist: requests
Requires-Dist: pymupdf
